jarvislabs/__init__.py
jarvislabs/app.py
jarvislabs/cli.py
jarvislabs/s3handler.py
jarvislabs/sample.py
jarvislabs/server.py
jarvislabs/templates.py
jarvislabs-0.1.66.dist-info/LICENSE
jarvislabs-0.1.66.dist-info/METADATA
jarvislabs-0.1.66.dist-info/WHEEL
jarvislabs-0.1.66.dist-info/entry_points.txt
jarvislabs-0.1.66.dist-info/top_level.txt
jarvislabs-0.1.66.dist-info/RECORD
